stem/__init__.py
stem/__version__.py
stem/additional_processes.py
stem/boundary.py
stem/default_materials.py
stem/field_generator.py
stem/geometry.py
stem/globals.py
stem/load.py
stem/mesh.py
stem/model.py
stem/model_part.py
stem/output.py
stem/plot_utils.py
stem/soil_material.py
stem/solver.py
stem/stem.py
stem/structural_material.py
stem/table.py
stem/utils.py
stem/water_processes.py
stem/IO/__init__.py
stem/IO/io_utils.py
stem/IO/kratos_additional_processes_io.py
stem/IO/kratos_boundaries_io.py
stem/IO/kratos_io.py
stem/IO/kratos_loads_io.py
stem/IO/kratos_material_io.py
stem/IO/kratos_output_io.py
stem/IO/kratos_solver_io.py
stem/IO/kratos_water_processes_io.py
stem_vibrations-1.2.3.dist-info/licenses/LICENSE
stem_vibrations-1.2.3.dist-info/licenses/NOTICE
stem_vibrations-1.2.3.dist-info/METADATA
stem_vibrations-1.2.3.dist-info/WHEEL
stem_vibrations-1.2.3.dist-info/top_level.txt
stem_vibrations-1.2.3.dist-info/RECORD
