Metadata-Version: 2.4
Name: STEM-Vibrations
Version: 1.2.3
Summary: STEM model
Home-page: https://github.com/StemVibrations/STEM
Author: STEM team
Classifier: Programming Language :: Python :: 3
Classifier: License :: OSI Approved :: BSD License
Classifier: Operating System :: Microsoft :: Windows
Classifier: Operating System :: Unix
Requires-Python: <3.12,>=3.9
License-File: LICENSE
License-File: NOTICE
Requires-Dist: numpy>=2.0.2
Requires-Dist: scipy>=1.13.1
Requires-Dist: plotly>=5.24.1
Requires-Dist: gmsh_utils==1.1.1
Requires-Dist: random_fields==1.0.1
Requires-Dist: UVEC==1.1.2
Provides-Extra: testing
Requires-Dist: pytest==7.4.2; extra == "testing"
Requires-Dist: pytest-cov>=6.0; extra == "testing"
Requires-Dist: tox>=4.23; extra == "testing"
Requires-Dist: mypy>=1.13; extra == "testing"
Requires-Dist: pre-commit==3.6.2; extra == "testing"
Requires-Dist: yapf==0.43.0; extra == "testing"
Requires-Dist: flake8==7.0.0; extra == "testing"
Requires-Dist: beautifulsoup4>=4.12; extra == "testing"
Requires-Dist: matplotlib>=3.9.3; extra == "testing"
Provides-Extra: docs
Requires-Dist: Sphinx==7.4.7; extra == "docs"
Requires-Dist: sphinx-rtd-theme==3.0.2; extra == "docs"
Requires-Dist: sphinxcontrib-bibtex==2.6.3; extra == "docs"
Dynamic: license-file
